bareasgi_jinja2/__init__.py
bareasgi_jinja2/jinja2_template_provider.py
bareasgi_jinja2/py.typed
bareasgi_jinja2-4.0.1.dist-info/LICENSE
bareasgi_jinja2-4.0.1.dist-info/WHEEL
bareasgi_jinja2-4.0.1.dist-info/METADATA
bareasgi_jinja2-4.0.1.dist-info/RECORD
