Metadata-Version: 2.1
Name: bareasgi-jinja2
Version: 4.0.1
Summary: Jinja2 support for bareasgi
Home-page: https://github.com/rob-blackbourn/bareasgi-jinja2
License: Apache-2.0
Author: Rob Blackbourn
Author-email: rob.blackbourn@gmail.com
Requires-Python: >=3.8,<4.0
Classifier: License :: OSI Approved :: Apache Software License
Classifier: Programming Language :: Python :: 3
Classifier: Programming Language :: Python :: 3.10
Classifier: Programming Language :: Python :: 3.8
Classifier: Programming Language :: Python :: 3.9
Requires-Dist: bareasgi (>=4.0.0,<5.0.0)
Requires-Dist: jinja2 (>=3.0,<4.0)
Project-URL: Repository, https://github.com/rob-blackbourn/bareasgi-jinja2
